autoparaselenium/__init__.py
autoparaselenium/browser_pool.py
autoparaselenium/models.py
autoparaselenium/setup_utils.py
autoparaselenium/browsers/__init__.py
autoparaselenium/browsers/chrome.py
autoparaselenium/browsers/firefox.py
autoparaselenium-0.3.1.dist-info/LICENSE
autoparaselenium-0.3.1.dist-info/METADATA
autoparaselenium-0.3.1.dist-info/WHEEL
autoparaselenium-0.3.1.dist-info/top_level.txt
autoparaselenium-0.3.1.dist-info/RECORD
