Metadata-Version: 2.1
Name: autoparaselenium
Version: 0.3.1
Summary: A library to make parallel selenium tests that automatically download and setup webdrivers
Author-email: Ronak Badhe <ronak.badhe@gmail.com>
License: MIT License
Keywords: selenium,automatic,parallel,testing
Classifier: Programming Language :: Python :: 3
Classifier: License :: OSI Approved :: MIT License
Classifier: Operating System :: OS Independent
Requires-Python: >=3.8
License-File: LICENSE
Requires-Dist: pytest (>=6.2.4)
Requires-Dist: pytest-parallel-39 (==0.1.0)
Requires-Dist: requests (>=2.24.0)
Requires-Dist: selenium (>=4.1.0)
